tm1637.py
gpiod_tm1637-1.3.7.dist-info/LICENSE.txt
gpiod_tm1637-1.3.7.dist-info/METADATA
gpiod_tm1637-1.3.7.dist-info/WHEEL
gpiod_tm1637-1.3.7.dist-info/top_level.txt
gpiod_tm1637-1.3.7.dist-info/RECORD
