Metadata-Version: 2.1
Name: gpiod-tm1637
Version: 1.3.7
Summary: GPIOD port from Raspberry Pi Python port from MicroPython library for TM1637 LED driver.
Home-page: https://gitlab.com/matsievskiysv/gpiod-tm1637
Author: Mike Causer
Author-email: mcauser@gmail.com
Maintainer: Sergey Matsievskiy
Maintainer-email: matsievskiysv@gmail.com
License: MIT
Keywords: tm1637 armbian seven segment led python
Classifier: Programming Language :: Python :: 3
Classifier: Development Status :: 5 - Production/Stable
Classifier: License :: OSI Approved :: MIT License
Requires-Python: >=3
License-File: LICENSE.txt
Requires-Dist: gpiod ~=2.1
